.gitignore
.gitlab-ci.yml
CONTRIBUTING.rst
LICENSE
README.md
environment.yml
requirements.txt
setup.py
docs/Makefile
docs/make.bat
docs/source/concept.rst
docs/source/conf.py
docs/source/hybridization.rst
docs/source/hybridvut.rst
docs/source/hybridvut.tools.rst
docs/source/index.rst
docs/source/intro.rst
docs/source/modules.rst
hybridvut/__init__.py
hybridvut/core.py
hybridvut/hybridizations.py
hybridvut/preprocessing.py
hybridvut.egg-info/PKG-INFO
hybridvut.egg-info/SOURCES.txt
hybridvut.egg-info/dependency_links.txt
hybridvut.egg-info/requires.txt
hybridvut.egg-info/top_level.txt
hybridvut/tools/RAS.py
hybridvut/tools/__init__.py
hybridvut/tools/iomath.py
hybridvut/tools/units.py
hybridvut/tools/utils.py
test/__init__.py
test/test_core.py